jupyterlab_datadog_rum/__init__.py
jupyterlab_datadog_rum/_version.py
jupyterlab_datadog_rum-0.0.2.data/data/share/jupyter/labextensions/jupyterlab-datadog-rum/package.json
jupyterlab_datadog_rum-0.0.2.data/data/share/jupyter/labextensions/jupyterlab-datadog-rum/schemas/jupyterlab-datadog-rum/package.json.orig
jupyterlab_datadog_rum-0.0.2.data/data/share/jupyter/labextensions/jupyterlab-datadog-rum/schemas/jupyterlab-datadog-rum/plugin.json
jupyterlab_datadog_rum-0.0.2.data/data/share/jupyter/labextensions/jupyterlab-datadog-rum/static/509.944afb925be174cb8f75.js
jupyterlab_datadog_rum-0.0.2.data/data/share/jupyter/labextensions/jupyterlab-datadog-rum/static/728.3d658b3e96ed2ce1e7a0.js
jupyterlab_datadog_rum-0.0.2.data/data/share/jupyter/labextensions/jupyterlab-datadog-rum/static/remoteEntry.513275e36e2a64636cbc.js
jupyterlab_datadog_rum-0.0.2.data/data/share/jupyter/labextensions/jupyterlab-datadog-rum/static/style.js
jupyterlab_datadog_rum-0.0.2.data/data/share/jupyter/labextensions/jupyterlab-datadog-rum/static/third-party-licenses.json
jupyterlab_datadog_rum-0.0.2.data/data/share/jupyter/labextensions/jupyterlab-datadog-rum/install.json
jupyterlab_datadog_rum-0.0.2.dist-info/METADATA
jupyterlab_datadog_rum-0.0.2.dist-info/WHEEL
jupyterlab_datadog_rum-0.0.2.dist-info/licenses/LICENSE
jupyterlab_datadog_rum-0.0.2.dist-info/RECORD
