Metadata-Version: 2.3
Name: jupyterlab_datadog_rum
Version: 0.0.2
Dynamic: Keywords
Summary: Datadog Real User Monitoring (RUM) for Jupyter Lab
Project-URL: Homepage, https://github.com/ctcjab/jupyterlab-datadog-rum
Project-URL: Repository, https://github.com/ctcjab/jupyterlab-datadog-rum.git
Author-email: Joshua Bronson <joshua.bronson@chicagotrading.com>
License: BSD 3-Clause License
License-File: LICENSE
Classifier: Framework :: Jupyter
Classifier: Framework :: Jupyter :: JupyterLab
Classifier: Framework :: Jupyter :: JupyterLab :: 4
Classifier: Framework :: Jupyter :: JupyterLab :: Extensions
Classifier: Framework :: Jupyter :: JupyterLab :: Extensions :: Prebuilt
Classifier: License :: OSI Approved :: BSD License
Classifier: Programming Language :: Python
Classifier: Programming Language :: Python :: 3
Classifier: Programming Language :: Python :: 3.8
Classifier: Programming Language :: Python :: 3.9
Classifier: Programming Language :: Python :: 3.10
Classifier: Programming Language :: Python :: 3.11
Classifier: Programming Language :: Python :: 3.12
Requires-Python: >=3.8
